cacheflow/__init__.py
cacheflow/base.py
cacheflow/builtin_components.py
cacheflow/cache/__init__.py
cacheflow/cache/base.py
cacheflow/cache/core.py
cacheflow/cli.py
cacheflow/executor.py
cacheflow/literal.py
cacheflow/python.py
cacheflow/storage/__init__.py
cacheflow/storage/actions.py
cacheflow/storage/controller.py
cacheflow/storage/json.py
cacheflow/web/__init__.py
cacheflow/web/base.py
cacheflow/web/json.py
cacheflow/web/main.py
cacheflow/web/ui/index.html
cacheflow/web/ui/static/css/app.9124eddd.css
cacheflow/web/ui/static/favicon.ico
cacheflow/web/ui/static/index.html
cacheflow/web/ui/static/js/app.664c5b71.js
cacheflow/web/ui/static/js/app.664c5b71.js.map
cacheflow/web/ui/static/js/chunk-vendors.9a7fdba6.js
cacheflow/web/ui/static/js/chunk-vendors.9a7fdba6.js.map
cacheflow-0.3.dist-info/entry_points.txt
cacheflow-0.3.dist-info/LICENSE.txt
cacheflow-0.3.dist-info/WHEEL
cacheflow-0.3.dist-info/METADATA
cacheflow-0.3.dist-info/RECORD
