Metadata-Version: 2.1
Name: cacheflow
Version: 0.3
Summary: Caching Workflow Engine
Home-page: https://gitlab.com/remram44/cacheflow
License: BSD-3-Clause
Keywords: workflow,execution,cache,caching,notebook
Author: Remi Rampin
Author-email: remi.rampin@nyu.edu
Requires-Python: >=3.6,<4.0
Classifier: Development Status :: 1 - Planning
Classifier: Environment :: Console
Classifier: Environment :: Web Environment
Classifier: Intended Audience :: End Users/Desktop
Classifier: Intended Audience :: Science/Research
Classifier: License :: OSI Approved :: BSD License
Classifier: Programming Language :: Python
Classifier: Programming Language :: Python :: 3
Classifier: Programming Language :: Python :: 3.6
Classifier: Programming Language :: Python :: 3.7
Classifier: Programming Language :: Python :: 3.8
Classifier: Programming Language :: SQL
Classifier: Programming Language :: Unix Shell
Classifier: Topic :: Scientific/Engineering
Classifier: Topic :: Scientific/Engineering :: Information Analysis
Classifier: Topic :: Scientific/Engineering :: Visualization
Classifier: Topic :: Software Development :: Build Tools
Classifier: Topic :: Software Development :: Interpreters
Classifier: Topic :: System :: Distributed Computing
Classifier: Topic :: Text Processing :: Markup
Classifier: Topic :: Utilities
Requires-Dist: PyYAML (>=5.3,<6.0)
Requires-Dist: cloudpickle (>=1.2,<2.0)
Requires-Dist: markdown (>=3,<4)
Requires-Dist: requests (>=2.22,<3.0)
Requires-Dist: tornado (>=6.0,<6.1)
Project-URL: Repository, https://gitlab.com/remram44/cacheflow
